ONRush/Rush.py
ONRush/__init__.py
Rush_db/Rush_db.py
Rush_db/__init__.py
ONRush-0.0.1.dist-info/LICENSE
ONRush-0.0.1.dist-info/METADATA
ONRush-0.0.1.dist-info/WHEEL
ONRush-0.0.1.dist-info/top_level.txt
ONRush-0.0.1.dist-info/RECORD
