Metadata-Version: 2.1
Name: ONRush
Version: 0.0.1
Summary: NO-SQL Packages Built upon SQLite
Home-page: UNKNOWN
Author: astroxiii (abderrahim mokhnache)
Author-email: <abderrahimokhnache@gmail.com>
License: UNKNOWN
Keywords: python,sqlite,sql,no-sql,db,database
Platform: UNKNOWN
Classifier: Development Status :: 3 - Alpha
Classifier: Intended Audience :: Developers
Classifier: Programming Language :: Python :: 3
Classifier: Operating System :: Unix
Classifier: Operating System :: MacOS :: MacOS X
Classifier: Operating System :: Microsoft :: Windows
License-File: LICENSE
